azul_client/__init__.py
azul_client/client.py
azul_client/config.py
azul_client/exceptions.py
azul_client/api/__init__.py
azul_client/api/base_api.py
azul_client/api/binaries_data.py
azul_client/api/binaries_meta.py
azul_client/api/features.py
azul_client/api/plugins.py
azul_client/api/purge.py
azul_client/api/security.py
azul_client/api/sources.py
azul_client/api/statistics.py
azul_client/api/users.py
azul_client/oidc/__init__.py
azul_client/oidc/callback.py
azul_client/oidc/oidc.py
azul_client-9.0.23.dist-info/METADATA
azul_client-9.0.23.dist-info/WHEEL
azul_client-9.0.23.dist-info/entry_points.txt
azul_client-9.0.23.dist-info/top_level.txt
azul_client-9.0.23.dist-info/RECORD
