Metadata-Version: 2.4
Name: azul-client
Version: 9.0.23
Summary: Interact with Azul using your terminal instead of clicking in the UI a thousand times!
Home-page: https://www.asd.gov.au/
Author: Azul
Author-email: azul@asd.gov.au
Classifier: Development Status :: 5 - Production/Stable
Classifier: License :: OSI Approved :: MIT License
Classifier: Programming Language :: Python
Classifier: Programming Language :: Python :: 3
Classifier: Programming Language :: Python :: 3.12
Classifier: Programming Language :: Python :: 3.13
Classifier: Programming Language :: Python :: 3.14
Classifier: Intended Audience :: Developers
Classifier: Topic :: Software Development :: Libraries
Requires-Python: >=3.12
Requires-Dist: cart
Requires-Dist: malpz
Requires-Dist: click
Requires-Dist: pendulum
Requires-Dist: rich
Requires-Dist: httpx
Requires-Dist: pydantic>2
Requires-Dist: pydantic-settings
Requires-Dist: tenacity
Requires-Dist: azul-bedrock
Dynamic: author
Dynamic: author-email
Dynamic: classifier
Dynamic: description
Dynamic: description-content-type
Dynamic: home-page
Dynamic: requires-dist
Dynamic: requires-python
Dynamic: summary
